Workbook

Sheet Dashboard
A1: SALES PERFORMANCE DASHBOARD
A4: Total Net Sales | C4: Total Profit | E4: Units Sold | G4: Orders
A5: =SUM('Sales Data'!L2:L65) -> 233850 | C5: =SUM('Sales Data'!N2:N65) -> 39020 | E5: =SUM('Sales Data'!G2:G65) -> 120 | G5: =COUNTA('Sales Data'!B2:B65) -> 64
A7: Overall Profit Margin | B7: =C5/A5 -> 0.1668591

Sheet Sales Data
A1: Date | B1: InvoiceNo | C1: ProductID | D1: ProductName | E1: Category | F1: Brand | G1: Quantity | H1: UnitPrice | I1: UnitCost | J1: Discount | K1: Gross Sales | L1: Net Sales | M1: Cost | N1: Profit | O1: Margin %
A2: 46266 | B2: INV001 | C2: P001 | D2: iPhone 15 | E2: Mobile | F2: Apple | G2: 2 | H2: 2800 | I2: 2300 | J2: 100 | K2: =G2*H2 -> 5600 | L2: =K2-J2 -> 5500 | M2: =G2*I2 -> 4600 | N2: =L2-M2 -> 900 | O2: =N2/L2 -> 0.16363636
A3: 46266 | B3: INV002 | C3: P002 | D3: Samsung S25 | E3: Mobile | F3: Samsung | G3: 1 | H3: 2500 | I3: 2000 | J3: 0 | K3: =G3*H3 -> 2500 | L3: =K3-J3 -> 2500 | M3: =G3*I3 -> 2000 | N3: =L3-M3 -> 500 | O3: =N3/L3 -> 0.2
A4: 46267 | B4: INV003 | C4: P003 | D4: LG TV | E4: TV | F4: LG | G4: 1 | H4: 3200 | I4: 2600 | J4: 200 | K4: =G4*H4 -> 3200 | L4: =K4-J4 -> 3000 | M4: =G4*I4 -> 2600 | N4: =L4-M4 -> 400 | O4: =N4/L4 -> 0.13333333
A5: 46268 | B5: INV004 | C5: P004 | D5: iPhone 15 Pro | E5: Mobile | F5: Apple | G5: 1 | H5: 3600 | I5: 3000 | J5: 150 | K5: =G5*H5 -> 3600 | L5: =K5-J5 -> 3450 | M5: =G5*I5 -> 3000 | N5: =L5-M5 -> 450 | O5: =N5/L5 -> 0.13043478
A6: 46268 | B6: INV005 | C6: P005 | D6: Samsung A55 | E6: Mobile | F6: Samsung | G6: 3 | H6: 1400 | I6: 1100 | J6: 100 | K6: =G6*H6 -> 4200 | L6: =K6-J6 -> 4100 | M6: =G6*I6 -> 3300 | N6: =L6-M6 -> 800 | O6: =N6/L6 -> 0.19512195
A7: 46269 | B7: INV006 | C7: P006 | D7: Sony Bravia 55 | E7: TV | F7: Sony | G7: 1 | H7: 3500 | I7: 2850 | J7: 200 | K7: =G7*H7 -> 3500 | L7: =K7-J7 -> 3300 | M7: =G7*I7 -> 2850 | N7: =L7-M7 -> 450 | O7: =N7/L7 -> 0.13636364
A8: 46270 | B8: INV007 | C8: P007 | D8: HP Pavilion Laptop | E8: Laptop | F8: HP | G8: 1 | H8: 3200 | I8: 2600 | J8: 150 | K8: =G8*H8 -> 3200 | L8: =K8-J8 -> 3050 | M8: =G8*I8 -> 2600 | N8: =L8-M8 -> 450 | O8: =N8/L8 -> 0.14754098
A9: 46271 | B9: INV008 | C9: P008 | D9: Dell Inspiron | E9: Laptop | F9: Dell | G9: 2 | H9: 2900 | I9: 2350 | J9: 200 | K9: =G9*H9 -> 5800 | L9: =K9-J9 -> 5600 | M9: =G9*I9 -> 4700 | N9: =L9-M9 -> 900 | O9: =N9/L9 -> 0.16071429
A10: 46272 | B10: INV009 | C10: P009 | D10: AirPods Pro | E10: Accessories | F10: Apple | G10: 2 | H10: 850 | I10: 650 | J10: 50 | K10: =G10*H10 -> 1700 | L10: =K10-J10 -> 1650 | M10: =G10*I10 -> 1300 | N10: =L10-M10 -> 350 | O10: =N10/L10 -> 0.21212121
A11: 46273 | B11: INV010 | C11: P010 | D11: Galaxy Buds | E11: Accessories | F11: Samsung | G11: 3 | H11: 550 | I11: 400 | J11: 0 | K11: =G11*H11 -> 1650 | L11: =K11-J11 -> 1650 | M11: =G11*I11 -> 1200 | N11: =L11-M11 -> 450 | O11: =N11/L11 -> 0.27272727
A12: 46274 | B12: INV011 | C12: P011 | D12: TCL 50 TV | E12: TV | F12: TCL | G12: 1 | H12: 2200 | I12: 1800 | J12: 100 | K12: =G12*H12 -> 2200 | L12: =K12-J12 -> 2100 | M12: =G12*I12 -> 1800 | N12: =L12-M12 -> 300 | O12: =N12/L12 -> 0.14285714
A13: 46275 | B13: INV012 | C13: P012 | D13: Lenovo ThinkPad | E13: Laptop | F13: Lenovo | G13: 1 | H13: 4100 | I13: 3400 | J13: 200 | K13: =G13*H13 -> 4100 | L13: =K13-J13 -> 3900 | M13: =G13*I13 -> 3400 | N13: =L13-M13 -> 500 | O13: =N13/L13 -> 0.12820513
... A65: 46356 | B65: INV064 | C65: P020 | D65: Xiaomi Redmi Note | E65: Mobile | F65: Xiaomi | G65: 4 | H65: 950 | I65: 700 | J65: 100 | K65: =G65*H65 -> 3800 | L65: =K65-J65 -> 3700 | M65: =G65*I65 -> 2800 | N65: =L65-M65 -> 900 | O65: =N65/L65 -> 0.24324324

Sheet Monthly Summary
A1: Month | B1: Quantity | C1: Net Sales | D1: Profit | E1: Orders
A2: Sep-2026 | B2: =SUMIFS('Sales Data'!G:G,'Sales Data'!A:A,">="&DATEVALUE("01/09/2026"),'Sales Data'!A:A,"<="&DATEVALUE("30/09/2026")) -> 37 | C2: =SUMIFS('Sales Data'!L:L,'Sales Data'!A:A,">="&DATEVALUE("01/09/2026"),'Sales Data'!A:A,"<="&DATEVALUE("30/09/2026")) -> 68130 | D2: =SUMIFS('Sales Data'!N:N,'Sales Data'!A:A,">="&DATEVALUE("01/09/2026"),'Sales Data'!A:A,"<="&DATEVALUE("30/09/2026")) -> 11550 | E2: =COUNTIFS('Sales Data'!A:A,">="&DATEVALUE("01/09/2026"),'Sales Data'!A:A,"<="&DATEVALUE("30/09/2026")) -> 22
A3: Oct-2026 | B3: =SUMIFS('Sales Data'!G:G,'Sales Data'!A:A,">="&DATEVALUE("01/10/2026"),'Sales Data'!A:A,"<="&DATEVALUE("31/10/2026")) -> 32 | C3: =SUMIFS('Sales Data'!L:L,'Sales Data'!A:A,">="&DATEVALUE("01/10/2026"),'Sales Data'!A:A,"<="&DATEVALUE("31/10/2026")) -> 72250 | D3: =SUMIFS('Sales Data'!N:N,'Sales Data'!A:A,">="&DATEVALUE("01/10/2026"),'Sales Data'!A:A,"<="&DATEVALUE("31/10/2026")) -> 11750 | E3: =COUNTIFS('Sales Data'!A:A,">="&DATEVALUE("01/10/2026"),'Sales Data'!A:A,"<="&DATEVALUE("31/10/2026")) -> 20
A4: Nov-2026 | B4: =SUMIFS('Sales Data'!G:G,'Sales Data'!A:A,">="&DATEVALUE("01/11/2026"),'Sales Data'!A:A,"<="&DATEVALUE("30/11/2026")) -> 51 | C4: =SUMIFS('Sales Data'!L:L,'Sales Data'!A:A,">="&DATEVALUE("01/11/2026"),'Sales Data'!A:A,"<="&DATEVALUE("30/11/2026")) -> 93470 | D4: =SUMIFS('Sales Data'!N:N,'Sales Data'!A:A,">="&DATEVALUE("01/11/2026"),'Sales Data'!A:A,"<="&DATEVALUE("30/11/2026")) -> 15720 | E4: =COUNTIFS('Sales Data'!A:A,">="&DATEVALUE("01/11/2026"),'Sales Data'!A:A,"<="&DATEVALUE("30/11/2026")) -> 22

Sheet Category Summary
A1: Category | B1: Quantity | C1: Net Sales | D1: Profit
A2: Mobile | B2: =SUMIF('Sales Data'!E:E,A2,'Sales Data'!G:G) -> 45 | C2: =SUMIF('Sales Data'!E:E,A2,'Sales Data'!L:L) -> 89750 | D2: =SUMIF('Sales Data'!E:E,A2,'Sales Data'!N:N) -> 15700
A3: TV | B3: =SUMIF('Sales Data'!E:E,A3,'Sales Data'!G:G) -> 17 | C3: =SUMIF('Sales Data'!E:E,A3,'Sales Data'!L:L) -> 48500 | D3: =SUMIF('Sales Data'!E:E,A3,'Sales Data'!N:N) -> 6900
A4: Laptop | B4: =SUMIF('Sales Data'!E:E,A4,'Sales Data'!G:G) -> 17 | C4: =SUMIF('Sales Data'!E:E,A4,'Sales Data'!L:L) -> 56650 | D4: =SUMIF('Sales Data'!E:E,A4,'Sales Data'!N:N) -> 8300
A5: Accessories | B5: =SUMIF('Sales Data'!E:E,A5,'Sales Data'!G:G) -> 32 | C5: =SUMIF('Sales Data'!E:E,A5,'Sales Data'!L:L) -> 17950 | D5: =SUMIF('Sales Data'!E:E,A5,'Sales Data'!N:N) -> 4370
A6: Tablet | B6: =SUMIF('Sales Data'!E:E,A6,'Sales Data'!G:G) -> 9 | C6: =SUMIF('Sales Data'!E:E,A6,'Sales Data'!L:L) -> 21000 | D6: =SUMIF('Sales Data'!E:E,A6,'Sales Data'!N:N) -> 3750
